{
    "academic_position": {
        "label": "ขอตําแหน่งทางวิชาการ",
        "items": [
            {
                "id": "c1",
                "label": "เอกสารวิชาการรับรอง",
                "score": 20
            },
            {
                "id": "c2",
                "label": "งานวิจัยตีพิมพ์ระดับชาติ",
                "score": 30
            },
            {
                "id": "c3",
                "label": "งานวิจัยตีพิมพ์ระดับนานาชาติ",
                "score": 50
            }
        ]
    }
}